codenerix_corporate/__init__.py
codenerix_corporate/admin.py
codenerix_corporate/apps.py
codenerix_corporate/forms.py
codenerix_corporate/models.py
codenerix_corporate/urls.py
codenerix_corporate/views.py
codenerix_corporate/migrations/0001_initial.py
codenerix_corporate/migrations/0002_remove_corporateimage_alias.py
codenerix_corporate/migrations/0003_auto_20180118_1757.py
codenerix_corporate/migrations/0004_alter_corporateimage_city_and_more.py
codenerix_corporate/migrations/__init__.py
codenerix_corporate/migrations/__pycache__/0001_initial.cpython-35.pyc
codenerix_corporate/migrations/__pycache__/0001_initial.cpython-39.pyc
codenerix_corporate/migrations/__pycache__/0002_remove_corporateimage_alias.cpython-35.pyc
codenerix_corporate/migrations/__pycache__/0002_remove_corporateimage_alias.cpython-39.pyc
codenerix_corporate/migrations/__pycache__/0003_auto_20180118_1757.cpython-35.pyc
codenerix_corporate/migrations/__pycache__/0003_auto_20180118_1757.cpython-39.pyc
codenerix_corporate/migrations/__pycache__/0004_alter_corporateimage_city_and_more.cpython-39.pyc
codenerix_corporate/migrations/__pycache__/__init__.cpython-35.pyc
codenerix_corporate/migrations/__pycache__/__init__.cpython-39.pyc
codenerix_corporate/static/corporate/corporateimages_rows.html
django_codenerix_corporate-4.0.1.dist-info/LICENSE
django_codenerix_corporate-4.0.1.dist-info/METADATA
django_codenerix_corporate-4.0.1.dist-info/WHEEL
django_codenerix_corporate-4.0.1.dist-info/top_level.txt
django_codenerix_corporate-4.0.1.dist-info/RECORD
